goerrpy/__init__.py
goerrpy/decorators.py
goerrpy-1.0.2.dist-info/METADATA
goerrpy-1.0.2.dist-info/WHEEL
goerrpy-1.0.2.dist-info/top_level.txt
goerrpy-1.0.2.dist-info/RECORD
